pkpd/__init__.py
tiva-0.1.dist-info/METADATA
tiva-0.1.dist-info/WHEEL
tiva-0.1.dist-info/top_level.txt
tiva-0.1.dist-info/RECORD
