Metadata-Version: 2.1
Name: tiva
Version: 0.1
Summary: Python PKPD Libray
Home-page: https://github.com/vitaldb/pkpd
Author: Hyung-Chul Lee
Author-email: vital@snu.ac.kr
Classifier: Programming Language :: Python :: 3
Classifier: License :: OSI Approved :: MIT License
Classifier: Operating System :: OS Independent
Requires-Dist: numpy
